{"cameraMode":{"drawMode":0,"name":"Shaded","section":"Shading Mode"},"sceneLighting":true,"audioPlay":false,"sceneViewState":{"m_AlwaysRefresh":false,"showFog":true,"showSkybox":true,"showFlares":true,"showImageEffects":true,"showParticleSystems":true,"showVisualEffectGraphs":true,"m_FxEnabled":true},"in2DMode":false,"pivot":{"x":24.34416961669922,"y":-7.71068811416626,"z":-27.080303192138673},"rotation":{"x":0.0023116348311305048,"y":-0.9898743629455566,"z":0.0873568058013916,"w":0.10469264537096024},"size":5.066025733947754,"orthographic":false}